.DS_Store
demyst/.DS_Store
demyst/common/__init__.py
demyst/common/config.py
demyst/common/connectors.py
demyst/common/pii.py
demyst/common/util.py
demyst_common-0.9.0.dist-info/METADATA
demyst_common-0.9.0.dist-info/WHEEL
demyst_common-0.9.0.dist-info/top_level.txt
demyst_common-0.9.0.dist-info/RECORD
